tiff_tf_loader/__init__.py
tiff_tf_loader/loader.py
tiff_tf_loader-0.1.1.dist-info/licenses/LICENSE
tiff_tf_loader-0.1.1.dist-info/METADATA
tiff_tf_loader-0.1.1.dist-info/WHEEL
tiff_tf_loader-0.1.1.dist-info/top_level.txt
tiff_tf_loader-0.1.1.dist-info/RECORD
