Metadata-Version: 2.4
Name: tiff-tf-loader
Version: 0.1.1
Summary: Load TIFF images into TensorFlow datasets using rasterio
Home-page: https://github.com/haribabugitwork/tiff-tf-loader
Author: Hari Babu KVN
Author-email: haribabuatwork@gmail.com
Classifier: Programming Language :: Python :: 3
Classifier: License :: OSI Approved :: MIT License
Classifier: Operating System :: OS Independent
Requires-Python: >=3.7
License-File: LICENSE
Requires-Dist: tensorflow>=2.8
Requires-Dist: rasterio
Requires-Dist: scikit-learn
Requires-Dist: numpy
Dynamic: author
Dynamic: author-email
Dynamic: classifier
Dynamic: description
Dynamic: description-content-type
Dynamic: home-page
Dynamic: license-file
Dynamic: requires-dist
Dynamic: requires-python
Dynamic: summary
